wpcEXEbuild/__init__.py
wpcEXEbuild/script.py
wpcEXEbuild-0.0.2.dist-info/LICENSE
wpcEXEbuild-0.0.2.dist-info/METADATA
wpcEXEbuild-0.0.2.dist-info/WHEEL
wpcEXEbuild-0.0.2.dist-info/entry_points.txt
wpcEXEbuild-0.0.2.dist-info/top_level.txt
wpcEXEbuild-0.0.2.dist-info/RECORD
