Metadata-Version: 2.1
Name: wpcEXEbuild
Version: 0.0.2
Summary: WPC EXE builder
Author: chunglee_people
Author-email: wu@wpc.com.tw
License: MIT
Keywords: wpc,executable,standalone,packaging,app,apps,exe
Platform: UNKNOWN
Requires-Python: >=3.8
License-File: LICENSE
Requires-Dist: pyinstaller (>=5.3)
